<annotation>
	<folder>dataset</folder>
	<filename>513.jpg</filename>
	<path>D:\projects\MainProject\Weapon Detection\Datapreparation\dataset\513.jpg</path>
	<source>
		<database>Unknown</database>
	</source>
	<size>
		<width>5181</width>
		<height>3454</height>
		<depth>3</depth>
	</size>
	<segmented>0</segmented>
	<object>
		<name>person</name>
		<pose>Unspecified</pose>
		<truncated>0</truncated>
		<difficult>0</difficult>
		<bndbox>
			<xmin>2390</xmin>
			<ymin>1417</ymin>
			<xmax>2855</xmax>
			<ymax>2812</ymax>
		</bndbox>
	</object>
</annotation>
